shbagents/__init__.py
shbagents/_version.py
shbagents/agent_types.py
shbagents/agents.py
shbagents/default_tools.py
shbagents/memory.py
shbagents/model.py
shbagents/monitoring.py
shbagents/prompt.py
shbagents/tool.py
shbagents/utils.py
shbagents-0.1.3.dist-info/licenses/LICENSE
shbagents-0.1.3.dist-info/METADATA
shbagents-0.1.3.dist-info/WHEEL
shbagents-0.1.3.dist-info/top_level.txt
shbagents-0.1.3.dist-info/RECORD
